pow2.v
module pow_2_function #(
    parameter w = 16,
    parameter int_width = 3,
    parameter frc_width = 12
)(
    input wire [w-1 : 0] x,
    output wire [w-1 : 0] y
);
    wire x_sign = x[w-1];
    wire [frc_width-1 : 0] x_frc  = x[frc_width-1 : 0];
    wire [int_width-1 : 0] x_int  = x[w-2 : frc_width];

    wire [w-1 : 0] base    = {1'b1,x_frc};
    wire shift_needed = (x_int != {int_width{1'b0}}) && (x_int != {int_width{1'b1}});
    wire [w-1 : 0] y1, y2;

    assign y1 = x_sign ? (base >>> 1) : base ;
    assign y2 = x_sign ? (y1 >>> 1) : (y1 <<< 1);

    assign y = shift_needed ? y2 : y1;


endmodule

core.v
module core #(    //#() called module's parameter port list
    // Constants
    localparam tau_shift = 1,
    localparam time_shift = 7,
    localparam total_shift = tau_shift + time_shift,

    // Widths
    parameter int_width = 3,
    parameter frc_width = 12,
    localparam w = 1 + int_width + frc_width, // Total Width
    
    // Coefficient 'a'
    localparam signed [w-1 : 0] a = 16'd2867
)(
    input  wire clk,
    input  wire rst,
    input  wire signed [w-1 : 0] i,
    output reg  signed [w-1 : 0] v,
    output reg  signed [w-1 : 0] w_out
);

    wire signed [w-1 : 0] pow2_pos, pow2_neg;
    wire signed [19 : 0] z1, z2, z5;
    wire signed [19 : 0] v_ext, w_ext, i_ext, diff_ext;
    wire signed [w-1 : 0] z3, z4, z6, z7;

    assign v_ext = {{4{v[w-1]}}, v};
    assign w_ext = {{4{w_out[w-1]}}, w_out};
    assign i_ext = {{4{i[w-1]}}, i};
    
    wire signed [19:0] z5_raw;
    localparam signed [19:0] THRESHOLD = 20'd175;

    // Instantiation
    pow_2_function #(
        .w(w), 
        .int_width(int_width), 
        .frc_width(frc_width)
    ) positive_v (.x(v), .y(pow2_pos));
    pow_2_function #(
        .w(w), 
        .int_width(int_width), 
        .frc_width(frc_width)
    ) negative_v (.x(-v), .y(pow2_neg));

    assign diff_ext = {{4{pow2_neg[w-1]}} , pow2_neg} - {{4{pow2_pos[w-1]}}, pow2_pos};
    assign z1 = (diff_ext <<< 1) + diff_ext;
    assign z2 = (v_ext <<< 2) + v_ext;
    assign z3 = v + a - (w_out >>> 1);

    assign z4 = (z3 + 128) >>> total_shift;
    //assign z4 = (z3) >>> total_shift;
    assign z5_raw = z1 + z2 - w_ext + i_ext;
    assign z5 = (z5_raw > -THRESHOLD && z5_raw < THRESHOLD) ? 20'd0 : z5_raw;
    assign z6 = w_out + z4;
    assign z7 = v + $signed((z5 + 64) >>> time_shift);
    //assign z7 = v + $signed((z5) >>> time_shift);
    // Combinational Logic
    // assign z1 = ((pow2_neg - pow2_pos) <<< 1) + (pow2_neg - pow2_pos);  // 3 * (2^-v - 2^v)
    // assign z2 = (v <<< 2) + v;                                          // 5 * v
    // assign z3 = v + a - (w_out >>> 1);                                  // v + a - 0.5w
    // assign z4 = z3 >>> total_shift;                                     // (dt/tau) * z3
    // assign z5 = z1 + z2 - w_out + i;                                    // 5v + g(v) - w + I
    
    // assign z6 = w_out + z4;             // Next W
    // assign z7 = (z5 >>> time_shift) + v; // Next V (Fixed: used time_shift)
    
    // Sequential Logic
    always @(posedge clk or posedge rst) begin
      if (rst) begin
        v <= 16'hECE1;
        w_out <= 16'hF600;
      end
      else begin
        v <= z7;
        w_out <= z6;
      end 
    end
    
endmodule

testbench.v
`timescale 1ns / 1ps 

module tb_fhn;
    // Signal Declarations
    reg clk, rst;
    reg signed [15 : 0] i_stim;
    wire signed [15 : 0] v_out, w_out;

    // Fixed-Point Parameters (Q3.12)
    localparam FRC_BITS = 12;
    real scaling_factor = 4096.0;

    // Instantiate the Core
    core uut(
        .clk(clk), 
        .rst(rst), 
        .i(i_stim),
        .v(v_out), 
        .w_out(w_out)
    );

    // Clock Generation (100 MHz -> 10ns period)
    initial clk = 0;
    always #5 clk = ~clk;
    
    integer file;

    initial begin 
        // Optional: Create VCD for GTKWave
        $dumpfile("fhn_sim.vcd");
        $dumpvars(0, tb_fhn);

        // Open CSV file for Python plotting
        file = $fopen("data.csv", "w");
        if (file == 0) begin
            $display("Error: Could not open file.");
            $finish;
        end
        
        // Header for CSV
        $fdisplay(file, "time_step,v_raw,v_float");

        // 1. Initialization
        rst = 1; 
        i_stim = 0;
        #100;
        
        // 2. Release Reset
        rst = 0;
        #100; 

        // 3. Apply Stimulus
        // Value 3277 corresponds to ~0.8 in Q3.12 format
        // Paper uses I=0.5 (2048) or I=1.0 (4096) for testing.
        i_stim = 16'd4098; 
        $display("Applying Stimulus I = 0.8...");

        // Run for 4000 cycles (Spiking Phase)
        repeat (4000) begin
            @(posedge clk); // Wait for clock edge
            // Write simulation time, raw integer, and converted float approximation
            $fdisplay(file, "%0d,%d,%f", $time, $signed(v_out), $signed(v_out)/scaling_factor);
        end

        // 4. Remove Stimulus (Relaxation Phase)
        i_stim = 16'd0;
        $display("Removing Stimulus...");

        repeat (20000) begin
            @(posedge clk);
            $fdisplay(file, "%0d,%d,%f", $time, $signed(v_out), $signed(v_out)/scaling_factor);
        end

        $display("Simulation Finished. Data written to data.csv");
        $fclose(file);
        $finish;
    end

endmodule

fhn_sim.vcd
$date
	Sun Jan 18 13:46:29 2026
$end
$version
	Icarus Verilog
$end
$timescale
	1ps
$end
$scope module tb_fhn $end
$var wire 16 ! w_out [15:0] $end
$var wire 16 " v_out [15:0] $end
$var parameter 32 # FRC_BITS $end
$var reg 1 $ clk $end
$var reg 16 % i_stim [15:0] $end
$var reg 1 & rst $end
$var integer 32 ' file [31:0] $end
$var real 1 ( scaling_factor $end
$scope module uut $end
$var wire 1 $ clk $end
$var wire 16 ) i [15:0] $end
$var wire 1 & rst $end
$var wire 16 * z7 [15:0] $end
$var wire 16 + z6 [15:0] $end
$var wire 20 , z5_raw [19:0] $end
$var wire 20 - z5 [19:0] $end
$var wire 16 . z4 [15:0] $end
$var wire 16 / z3 [15:0] $end
$var wire 20 0 z2 [19:0] $end
$var wire 20 1 z1 [19:0] $end
$var wire 20 2 w_ext [19:0] $end
$var wire 20 3 v_ext [19:0] $end
$var wire 16 4 pow2_pos [15:0] $end
$var wire 16 5 pow2_neg [15:0] $end
$var wire 20 6 i_ext [19:0] $end
$var wire 20 7 diff_ext [19:0] $end
$var parameter 20 8 THRESHOLD $end
$var parameter 16 9 a $end
$var parameter 32 : frc_width $end
$var parameter 32 ; int_width $end
$var parameter 32 < tau_shift $end
$var parameter 32 = time_shift $end
$var parameter 33 > total_shift $end
$var parameter 34 ? w $end
$var reg 16 @ v [15:0] $end
$var reg 16 A w_out [15:0] $end
$scope module negative_v $end
$var wire 1 B shift_needed $end
$var wire 16 C x [15:0] $end
$var wire 16 D y2 [15:0] $end
$var wire 16 E y1 [15:0] $end
$var wire 16 F y [15:0] $end
$var wire 1 G x_sign $end
$var wire 3 H x_int [2:0] $end
$var wire 12 I x_frc [11:0] $end
$var wire 16 J base [15:0] $end
$var parameter 32 K frc_width $end
$var parameter 32 L int_width $end
$var parameter 34 M w $end
$upscope $end
$scope module positive_v $end
$var wire 1 N shift_needed $end
$var wire 16 O x [15:0] $end
$var wire 16 P y2 [15:0] $end
$var wire 16 Q y1 [15:0] $end
$var wire 16 R y [15:0] $end
$var wire 1 S x_sign $end
$var wire 3 T x_int [2:0] $end
$var wire 12 U x_frc [11:0] $end
$var wire 16 V base [15:0] $end
$var parameter 32 W frc_width $end
$var parameter 32 X int_width $end
$var parameter 34 Y w $end
$upscope $end
$upscope $end
$upscope $end
$enddefinitions $end
$comment Show the parameter values. $end
$dumpall
b10000 Y
b11 X
b1100 W
b10000 M
b11 L
b1100 K
b10000 ?
b1000 >
b111 =
b1 <
b11 ;
b1100 :
b101100110011 9
b10101111 8
b1100 #
$end
#0
$dumpvars
b1110011100001 V
b110011100001 U
b110 T
1S
b11100111000 R
b111001110000 Q
b11100111000 P
b1110110011100001 O
1N
b1001100011111 J
b1100011111 I
b1 H
0G
b10011000111110 F
b1001100011111 E
b10011000111110 D
b1001100011111 C
1B
b1111011000000000 A
b1110110011100001 @
b1111100000110 7
b0 6
b10011000111110 5
b11100111000 4
b11111110110011100001 3
b11111111011000000000 2
b101110100010010 1
b11111010000001100101 0
b1111110100010100 /
b1111111111111101 .
b11101110111 -
b11101110111 ,
b1111010111111101 +
b1110110011110000 *
b0 )
r4096 (
b10000000000000000000000000000011 '
1&
b0 %
0$
b1110110011100001 "
b1111011000000000 !
$end
#5000
1$
#10000
0$
#15000
1$
#20000
0$
#25000
1$
#30000
0$
#35000
1$
#40000
0$
#45000
1$
#50000
0$
#55000
1$
#60000
0$
#65000
1$
#70000
0$
#75000
1$
#80000
0$
#85000
1$
#90000
0$
#95000
1$
#100000
0$
0&
#105000
b11100111100 4
b11100111100 R
b101110010101100 1
b1111011100100 7
b10011000100000 5
b10011000100000 F
b11100111100 P
b10011000100000 D
b111001111000 Q
b1001100010000 E
b11101011111 -
b1001100010000 J
b1100010000 I
b1110110011111111 *
b1110011110000 V
b110011110000 U
b11111111010111111101 2
b1111010111111010 +
b1111010111111101 !
b1111010111111101 A
b11101011111 ,
b11111010000010110000 0
b11111110110011110000 3
b1001100010000 C
b1111110100100101 /
b1110110011110000 "
b1110110011110000 @
b1110110011110000 O
1$
#110000
0$
#115000
b11100111111 4
b11100111111 R
b101110001001001 1
b1111011000011 7
b10011000000010 5
b10011000000010 F
b11100111111 P
b10011000000010 D
b111001111111 Q
b1001100000001 E
b11101001010 -
b1001100000001 J
b1100000001 I
b1110110100001110 *
b1110011111111 V
b110011111111 U
b11111111010111111010 2
b1111010111110111 +
b1111010111111010 !
b1111010111111010 A
b11101001010 ,
b11111010000011111011 0
b11111110110011111111 3
b1001100000001 C
b1111110100110101 /
b1110110011111111 "
b1110110011111111 @
b1110110011111111 O
1$
#120000
0$
#125000
b11101000011 4
b11101000011 R
b101101111100011 1
b1111010100001 7
b10010111100100 5
b10010111100100 F
b11101000011 P
b10010111100100 D
b111010000111 Q
b1001011110010 E
b11100110010 -
b1001011110010 J
b1011110010 I
b1110110100011100 *
b1110100001110 V
b110100001110 U
b11111111010111110111 2
b1111010111110100 +
b1111010111110111 !
b1111010111110111 A
b11100110010 ,
b11111010000101000110 0
b11111110110100001110 3
b1001011110010 C
b1111110101000110 /
b1110110100001110 "
b1110110100001110 @
b1110110100001110 O
1$
#130000
0$
#135000
b11101000111 4
b11101000111 R
b101101110000011 1
b1111010000001 7
b10010111001000 5
b10010111001000 F
b11101000111 P
b10010111001000 D
b111010001110 Q
b1001011100100 E
b11100011011 -
b1001011100100 J
b1011100100 I
b1110110100101010 *
b1110100011100 V
b110100011100 U
b11111111010111110100 2
b1111010111110001 +
b1111010111110100 !
b1111010111110100 A
b11100011011 ,
b11111010000110001100 0
b11111110110100011100 3
b1001011100100 C
b1111110101010101 /
b1110110100011100 "
b1110110100011100 @
b1110110100011100 O
1$
#140000
0$
#145000
b11101001010 4
b11101001010 R
b101101100100110 1
b1111001100010 7
b10010110101100 5
b10010110101100 F
b11101001010 P
b10010110101100 D
b111010010101 Q
b1001011010110 E
b11100000111 -
b1001011010110 J
b1011010110 I
b1110110100111000 *
b1110100101010 V
b110100101010 U
b11111111010111110001 2
b1111010111101110 +
b1111010111110001 !
b1111010111110001 A
b11100000111 ,
b11111010000111010010 0
b11111110110100101010 3
b1001011010110 C
b1111110101100101 /
b1110110100101010 "
b1110110100101010 @
b1110110100101010 O
1$
#150000
0$
#155000
b11101001110 4
b11101001110 R
b101101011000110 1
b1111001000010 7
b10010110010000 5
b10010110010000 F
b11101001110 P
b10010110010000 D
b111010011100 Q
b1001011001000 E
b11011110000 -
b1001011001000 J
b1011001000 I
b1110110101000110 *
b1110100111000 V
b110100111000 U
b11111111010111101110 2
b1111010111101011 +
b1111010111101110 !
b1111010111101110 A
b11011110000 ,
b11111010001000011000 0
b11111110110100111000 3
b1001011001000 C
b1111110101110100 /
b1110110100111000 "
b1110110100111000 @
b1110110100111000 O
1$
#160000
0$
#165000
b11101010001 4
b11101010001 R
b101101001101001 1
b1111000100011 7
b10010101110100 5
b10010101110100 F
b11101010001 P
b10010101110100 D
b111010100011 Q
b1001010111010 E
b1111111111111110 .
b11011011100 -
b1001010111010 J
b1010111010 I
b1110110101010100 *
b1110101000110 V
b110101000110 U
b11111111010111101011 2
b1111010111101001 +
b1111010111101011 !
b1111010111101011 A
b11011011100 ,
b11111010001001011110 0
b11111110110101000110 3
b1001010111010 C
b1111110110000100 /
b1110110101000110 "
b1110110101000110 @
b1110110101000110 O
1$
#170000
0$
#175000
b11101010101 4
b11101010101 R
b101101000001001 1
b1111000000011 7
b10010101011000 5
b10010101011000 F
b11101010101 P
b10010101011000 D
b111010101010 Q
b1001010101100 E
b11011000100 -
b1001010101100 J
b1010101100 I
b1110110101100010 *
b1110101010100 V
b110101010100 U
b11111111010111101001 2
b1111010111100111 +
b1111010111101001 !
b1111010111101001 A
b11011000100 ,
b11111010001010100100 0
b11111110110101010100 3
b1001010101100 C
b1111110110010011 /
b1110110101010100 "
b1110110101010100 @
b1110110101010100 O
1$
#180000
0$
#185000
b11101011000 4
b11101011000 R
b101100110101100 1
b1110111100100 7
b10010100111100 5
b10010100111100 F
b11101011000 P
b10010100111100 D
b111010110001 Q
b1001010011110 E
b11010101111 -
b1001010011110 J
b1010011110 I
b1110110101101111 *
b1110101100010 V
b110101100010 U
b11111111010111100111 2
b1111010111100101 +
b1111010111100111 !
b1111010111100111 A
b11010101111 ,
b11111010001011101010 0
b11111110110101100010 3
b1001010011110 C
b1111110110100010 /
b1110110101100010 "
b1110110101100010 @
b1110110101100010 O
1$
#190000
0$
#195000
b11101011011 4
b11101011011 R
b101100101010101 1
b1110111000111 7
b10010100100010 5
b10010100100010 F
b11101011011 P
b10010100100010 D
b111010110111 Q
b1001010010001 E
b11010011011 -
b1001010010001 J
b1010010001 I
b1110110101111100 *
b1110101101111 V
b110101101111 U
b11111111010111100101 2
b1111010111100011 +
b1111010111100101 !
b1111010111100101 A
b11010011011 ,
b11111010001100101011 0
b11111110110101101111 3
b1001010010001 C
b1111110110110000 /
b1110110101101111 "
b1110110101101111 @
b1110110101101111 O
1$
#200000
b1110110110011100 *
b1011010011101 -
0$
b1011010011101 ,
b1000000000010 6
b1000000000010 %
b1000000000010 )
#205000
b11101100111 4
b11101100111 R
b101100000100011 1
b1110101100001 7
b10010011001000 5
b10010011001000 F
b11101100111 P
b10010011001000 D
b111011001110 Q
b1001001100100 E
b1011001001110 -
b1001001100100 J
b1001100100 I
b1110110111001001 *
b1110110011100 V
b110110011100 U
b11111111010111100011 2
b1111010111100001 +
b1111010111100011 !
b1111010111100011 A
b1011001001110 ,
b11111010010000001100 0
b11111110110110011100 3
b1001001100100 C
b1111110111011110 /
b1110110110011100 "
b1110110110011100 @
b1110110110011100 O
1$
#210000
0$
#215000
b11101110010 4
b11101110010 R
b101011011110100 1
b1110011111100 7
b10010001101110 5
b10010001101110 F
b11101110010 P
b10010001101110 D
b111011100100 Q
b1001000110111 E
b1011000000010 -
b1001000110111 J
b1000110111 I
b1110110111110101 *
b1110111001001 V
b110111001001 U
b11111111010111100001 2
b1111010111011111 +
b1111010111100001 !
b1111010111100001 A
b1011000000010 ,
b11111010010011101101 0
b11111110110111001001 3
b1001000110111 C
b1111111000001100 /
b1110110111001001 "
b1110110111001001 @
b1110110111001001 O
1$
#220000
0$
#225000
b11101111101 4
b11101111101 R
b101010111001011 1
b1110010011001 7
b10010000010110 5
b10010000010110 F
b11101111101 P
b10010000010110 D
b111011111010 Q
b1001000001011 E
b1010110110111 -
b1001000001011 J
b1000001011 I
b1110111000100000 *
b1110111110101 V
b110111110101 U
b11111111010111011111 2
b1111010111011101 +
b1111010111011111 !
b1111010111011111 A
b1010110110111 ,
b11111010010111001001 0
b11111110110111110101 3
b1001000001011 C
b1111111000111001 /
b1110110111110101 "
b1110110111110101 @
b1110110111110101 O
1$
#230000
0$
#235000
b11110001000 4
b11110001000 R
b101010010101000 1
b1110000111000 7
b10001111000000 5
b10001111000000 F
b11110001000 P
b10001111000000 D
b111100010000 Q
b1000111100000 E
b1010101101101 -
b1000111100000 J
b111100000 I
b1110111001001011 *
b1111000100000 V
b111000100000 U
b11111111010111011101 2
b1111010111011011 +
b1111010111011101 !
b1111010111011101 A
b1010101101101 ,
b11111010011010100000 0
b11111110111000100000 3
b1000111100000 C
b1111111001100101 /
b1110111000100000 "
b1110111000100000 @
b1110111000100000 O
1$
#240000
0$
#245000
b11110010010 4
b11110010010 R
b101001110001000 1
b1101111011000 7
b10001101101010 5
b10001101101010 F
b11110010010 P
b10001101101010 D
b111100100101 Q
b1000110110101 E
b1111111111111111 .
b1010100100110 -
b1000110110101 J
b110110101 I
b1110111001110101 *
b1111001001011 V
b111001001011 U
b11111111010111011011 2
b1111010111011010 +
b1111010111011011 !
b1111010111011011 A
b1010100100110 ,
b11111010011101110111 0
b11111110111001001011 3
b1000110110101 C
b1111111010010001 /
b1110111001001011 "
b1110111001001011 @
b1110111001001011 O
1$
#250000
0$
#255000
b11110011101 4
b11110011101 R
b101001001101011 1
b1101101111001 7
b10001100010110 5
b10001100010110 F
b11110011101 P
b10001100010110 D
b111100111010 Q
b1000110001011 E
b1010011011100 -
b1000110001011 J
b110001011 I
b1110111010011111 *
b1111001110101 V
b111001110101 U
b11111111010111011010 2
b1111010111011001 +
b1111010111011010 !
b1111010111011010 A
b1010011011100 ,
b11111010100001001001 0
b11111110111001110101 3
b1000110001011 C
b1111111010111011 /
b1110111001110101 "
b1110111001110101 @
b1110111001110101 O
1$
#260000
0$
#265000
b11110100111 4
b11110100111 R
b101000101010001 1
b1101100011011 7
b10001011000010 5
b10001011000010 F
b11110100111 P
b10001011000010 D
b111101001111 Q
b1000101100001 E
b1010010010101 -
b1000101100001 J
b101100001 I
b1110111011001000 *
b1111010011111 V
b111010011111 U
b11111111010111011001 2
b1111010111011000 +
b1111010111011001 !
b1111010111011001 A
b1010010010101 ,
b11111010100100011011 0
b11111110111010011111 3
b1000101100001 C
b1111111011100110 /
b1110111010011111 "
b1110111010011111 @
b1110111010011111 O
1$
#270000
0$
#275000
b11110110010 4
b11110110010 R
b101000000111010 1
b1101010111110 7
b10001001110000 5
b10001001110000 F
b11110110010 P
b10001001110000 D
b111101100100 Q
b1000100111000 E
b1010001001100 -
b1000100111000 J
b100111000 I
b1110111011110001 *
b1111011001000 V
b111011001000 U
b11111111010111011000 2
b1111010111010111 +
b1111010111011000 !
b1111010111011000 A
b1010001001100 ,
b11111010100111101000 0
b11111110111011001000 3
b1000100111000 C
b1111111100001111 /
b1110111011001000 "
b1110111011001000 @
b1110111011001000 O
1$
#280000
0$
#285000
b11110111100 4
b11110111100 R
b100111100100110 1
b1101001100010 7
b10001000011110 5
b10001000011110 F
b11110111100 P
b10001000011110 D
b111101111000 Q
b1000100001111 E
b1010000000110 -
b1000100001111 J
b100001111 I
b1110111100011001 *
b1111011110001 V
b111011110001 U
b11111111010111010111 2
b1111010111010110 +
b1111010111010111 !
b1111010111010111 A
b1010000000110 ,
b11111010101010110101 0
b11111110111011110001 3
b1000100001111 C
b1111111100111001 /
b1110111011110001 "
b1110111011110001 @
b1110111011110001 O
1$
#290000
0$
#295000
b11111000110 4
b11111000110 R
b100111000011000 1
b1101000001000 7
b10000111001110 5
b10000111001110 F
b11111000110 P
b10000111001110 D
b111110001100 Q
b1000011100111 E
b1001111000001 -
b1000011100111 J
b11100111 I
b1110111101000001 *
b1111100011001 V
b111100011001 U
b11111111010111010110 2
b1111010111010101 +
b1111010111010110 !
b1111010111010110 A
b1001111000001 ,
b11111010101101111101 0
b11111110111100011001 3
b1000011100111 C
b1111111101100001 /
b1110111100011001 "
b1110111100011001 @
b1110111100011001 O
1$
#300000
0$
#305000
b11111010000 4
b11111010000 R
b100110100001010 1
b1100110101110 7
b10000101111110 5
b10000101111110 F
b11111010000 P
b10000101111110 D
b111110100000 Q
b1000010111111 E
b0 .
b1001101111100 -
b1000010111111 J
b10111111 I
b1110111101101000 *
b1111101000001 V
b111101000001 U
b11111111010111010101 2
b1111010111010101 +
b1111010111010101 !
b1111010111010101 A
b1001101111100 ,
b11111010110001000101 0
b11111110111101000001 3
b1000010111111 C
b1111111110001010 /
b1110111101000001 "
b1110111101000001 @
b1110111101000001 O
1$
#310000
0$
#315000
b11111011010 4
b11111011010 R
b100110000000010 1
b1100101010110 7
b10000100110000 5
b10000100110000 F
b11111011010 P
b10000100110000 D
b111110110100 Q
b1000010011000 E
b1001100110111 -
b1000010011000 J
b10011000 I
b1110111110001110 *
b1111101101000 V
b111101101000 U
b1001100110111 ,
b11111010110100001000 0
b11111110111101101000 3
b1000010011000 C
b1111111110110001 /
b1110111101101000 "
b1110111101101000 @
b1110111101101000 O
1$
#320000
0$
#325000
b11111100011 4
b11111100011 R
b100101100000011 1
b1100100000001 7
b10000011100100 5
b10000011100100 F
b11111100011 P
b10000011100100 D
b111111000111 Q
b1000001110010 E
b1001011110110 -
b1000001110010 J
b1110010 I
b1110111110110100 *
b1111110001110 V
b111110001110 U
b1001011110110 ,
b11111010110111000110 0
b11111110111110001110 3
b1000001110010 C
b1111111111010111 /
b1110111110001110 "
b1110111110001110 @
b1110111110001110 O
1$
#330000
0$
#335000
b11111101101 4
b11111101101 R
b100101000000001 1
b1100010101011 7
b10000010011000 5
b10000010011000 F
b11111101101 P
b10000010011000 D
b111111011010 Q
b1000001001100 E
b1001010110010 -
b1000001001100 J
b1001100 I
b1110111111011001 *
b1111110110100 V
b111110110100 U
b1001010110010 ,
b11111010111010000100 0
b11111110111110110100 3
b1000001001100 C
b1111111111111101 /
b1110111110110100 "
b1110111110110100 @
b1110111110110100 O
1$
#340000
0$
#345000
b11111110110 4
b11111110110 R
b100100100001000 1
b1100001011000 7
b10000001001110 5
b10000001001110 F
b11111110110 P
b10000001001110 D
b111111101100 Q
b1000000100111 E
b1001001110010 -
b1000000100111 J
b100111 I
b1110111111111110 *
b1111111011001 V
b111111011001 U
b1001001110010 ,
b11111010111100111101 0
b11111110111111011001 3
b1000000100111 C
b100010 /
b1110111111011001 "
b1110111111011001 @
b1110111111011001 O
1$
#350000
0$
#355000
b11111111111 4
b11111111111 R
b100100000001111 1
b1100000000101 7
b10000000000100 5
b10000000000100 F
b11111111111 P
b10000000000100 D
b111111111111 Q
b1000000000010 E
b1001000110010 -
b1000000000010 J
b10 I
b1111000000100010 *
b1111111111110 V
b111111111110 U
b1001000110010 ,
b11111010111111110110 0
b11111110111111111110 3
b1000000000010 C
b1000111 /
b1110111111111110 "
b1110111111111110 @
b1110111111111110 O
1$
#360000
0$
#365000
b10000001000 P
b11111110111100 D
b1111111011110 5
b1111111011110 F
b100000010001 Q
b100011101100111 1
b1011111001101 7
b100000010001 4
b100000010001 R
b1111111011110 E
0B
0N
b1001000111110 -
b1111111011110 J
b111111011110 I
b0 H
b1111000001000110 *
b1000000100010 V
b100010 U
b111 T
b1001000111110 ,
b11111011000010101010 0
b11111111000000100010 3
b111111011110 C
b1101011 /
b1111000000100010 "
b1111000000100010 @
b1111000000100010 O
1$
#370000
0$
#375000
b10000010001 P
b11111101110100 D
b100000100011 4
b100000100011 R
b100011011000101 1
b1011110010111 7
b1111110111010 5
b1111110111010 F
b100000100011 Q
b1111110111010 E
b1111010111010110 +
b1 .
b1001001010000 -
b1111110111010 J
b111110111010 I
b1111000001101011 *
b1000001000110 V
b1000110 U
b1001001010000 ,
b11111011000101011110 0
b11111111000001000110 3
b111110111010 C
b10001111 /
b1111000001000110 "
b1111000001000110 @
b1111000001000110 O
1$
#380000
0$
#385000
b10000011010 P
b11111100101010 D
b100000110101 4
b100000110101 R
b100011000100000 1
b1011101100000 7
b1111110010101 5
b1111110010101 F
b100000110101 Q
b1111110010101 E
b1001001100011 -
b1111110010101 J
b111110010101 I
b1111000010010000 *
b1000001101011 V
b1101011 U
b11111111010111010110 2
b1111010111010111 +
b1111010111010110 !
b1111010111010110 A
b1001001100011 ,
b11111011001000010111 0
b11111111000001101011 3
b111110010101 C
b10110011 /
b1111000001101011 "
b1111000001101011 @
b1111000001101011 O
1$
#390000
0$
#395000
b10000100100 P
b11111011100000 D
b100001001000 4
b100001001000 R
b100010101111000 1
b1011100101000 7
b1111101110000 5
b1111101110000 F
b100001001000 Q
b1111101110000 E
b1001001110011 -
b1111101110000 J
b111101110000 I
b1111000010110101 *
b1000010010000 V
b10010000 U
b11111111010111010111 2
b1111010111011000 +
b1111010111010111 !
b1111010111010111 A
b1001001110011 ,
b11111011001011010000 0
b11111111000010010000 3
b111101110000 C
b11011000 /
b1111000010010000 "
b1111000010010000 @
b1111000010010000 O
1$
#400000
0$
#405000
b10000101101 P
b11111010010110 D
b100001011010 4
b100001011010 R
b100010011010011 1
b1011011110001 7
b1111101001011 5
b1111101001011 F
b100001011010 Q
b1111101001011 E
b1001010000110 -
b1111101001011 J
b111101001011 I
b1111000011011010 *
b1000010110101 V
b10110101 U
b11111111010111011000 2
b1111010111011001 +
b1111010111011000 !
b1111010111011000 A
b1001010000110 ,
b11111011001110001001 0
b11111111000010110101 3
b111101001011 C
b11111100 /
b1111000010110101 "
b1111000010110101 @
b1111000010110101 O
1$
#410000
0$
#415000
b10000110110 P
b11111001001100 D
b100001101101 4
b100001101101 R
b100010000101011 1
b1011010111001 7
b1111100100110 5
b1111100100110 F
b100001101101 Q
b1111100100110 E
b1001010010110 -
b1111100100110 J
b111100100110 I
b1111000011111111 *
b1000011011010 V
b11011010 U
b11111111010111011001 2
b1111010111011010 +
b1111010111011001 !
b1111010111011001 A
b1001010010110 ,
b11111011010001000010 0
b11111111000011011010 3
b111100100110 C
b100100001 /
b1111000011011010 "
b1111000011011010 @
b1111000011011010 O
1$
#420000
0$
#425000
b10000111111 P
b11111000000010 D
b100001111111 4
b100001111111 R
b100001110000110 1
b1011010000010 7
b1111100000001 5
b1111100000001 F
b100001111111 Q
b1111100000001 E
b1001010101001 -
b1111100000001 J
b111100000001 I
b1111000100100100 *
b1000011111111 V
b11111111 U
b11111111010111011010 2
b1111010111011011 +
b1111010111011010 !
b1111010111011010 A
b1001010101001 ,
b11111011010011111011 0
b11111111000011111111 3
b111100000001 C
b101000101 /
b1111000011111111 "
b1111000011111111 @
b1111000011111111 O
1$
#430000
0$
#435000
b10001001001 P
b11110110111000 D
b100010010010 4
b100010010010 R
b100001011011110 1
b1011001001010 7
b1111011011100 5
b1111011011100 F
b100010010010 Q
b1111011011100 E
b1001010111001 -
b1111011011100 J
b111011011100 I
b1111000101001001 *
b1000100100100 V
b100100100 U
b11111111010111011011 2
b1111010111011100 +
b1111010111011011 !
b1111010111011011 A
b1001010111001 ,
b11111011010110110100 0
b11111111000100100100 3
b111011011100 C
b101101010 /
b1111000100100100 "
b1111000100100100 @
b1111000100100100 O
1$
#440000
0$
#445000
b10001010010 P
b11110101101110 D
b100010100100 4
b100010100100 R
b100001000111001 1
b1011000010011 7
b1111010110111 5
b1111010110111 F
b100010100100 Q
b1111010110111 E
b10 .
b1001011001100 -
b1111010110111 J
b111010110111 I
b1111000101101111 *
b1000101001001 V
b101001001 U
b11111111010111011100 2
b1111010111011110 +
b1111010111011100 !
b1111010111011100 A
b1001011001100 ,
b11111011011001101101 0
b11111111000101001001 3
b111010110111 C
b110001110 /
b1111000101001001 "
b1111000101001001 @
b1111000101001001 O
1$
#450000
0$
#455000
b10001011011 P
b11110100100010 D
b100010110111 4
b100010110111 R
b100000110001110 1
b1010111011010 7
b1111010010001 5
b1111010010001 F
b100010110111 Q
b1111010010001 E
b1001011011101 -
b1111010010001 J
b111010010001 I
b1111000110010101 *
b1000101101111 V
b101101111 U
b11111111010111011110 2
b1111010111100000 +
b1111010111011110 !
b1111010111011110 A
b1001011011101 ,
b11111011011100101011 0
b11111111000101101111 3
b111010010001 C
b110110011 /
b1111000101101111 "
b1111000101101111 @
b1111000101101111 O
1$
#460000
0$
#465000
b10001100101 P
b11110011010110 D
b100011001010 4
b100011001010 R
b100000011100011 1
b1010110100001 7
b1111001101011 5
b1111001101011 F
b100011001010 Q
b1111001101011 E
b1001011101110 -
b1111001101011 J
b111001101011 I
b1111000110111011 *
b1000110010101 V
b110010101 U
b11111111010111100000 2
b1111010111100010 +
b1111010111100000 !
b1111010111100000 A
b1001011101110 ,
b11111011011111101001 0
b11111111000110010101 3
b111001101011 C
b111011000 /
b1111000110010101 "
b1111000110010101 @
b1111000110010101 O
1$
#470000
0$
#475000
b10001101110 P
b11110010001010 D
b100011011101 4
b100011011101 R
b100000000111000 1
b1010101101000 7
b1111001000101 5
b1111001000101 F
b100011011101 Q
b1111001000101 E
b1001011111111 -
b1111001000101 J
b111001000101 I
b1111000111100001 *
b1000110111011 V
b110111011 U
b11111111010111100010 2
b1111010111100100 +
b1111010111100010 !
b1111010111100010 A
b1001011111111 ,
b11111011100010100111 0
b11111111000110111011 3
b111001000101 C
b111111101 /
b1111000110111011 "
b1111000110111011 @
b1111000110111011 O
1$
#480000
0$
#485000
b10001111000 P
b11110000111110 D
b100011110000 4
b100011110000 R
b11111110001101 1
b1010100101111 7
b1111000011111 5
b1111000011111 F
b100011110000 Q
b1111000011111 E
b1001100010000 -
b1111000011111 J
b111000011111 I
b1111001000000111 *
b1000111100001 V
b111100001 U
b11111111010111100100 2
b1111010111100110 +
b1111010111100100 !
b1111010111100100 A
b1001100010000 ,
b11111011100101100101 0
b11111111000111100001 3
b111000011111 C
b1000100010 /
b1111000111100001 "
b1111000111100001 @
b1111000111100001 O
1$
#490000
0$
